pycachera/__init__.py
pycachera/cacher.py
pycachera/mpi.py
pycachera-4.5.1.dist-info/LICENSE
pycachera-4.5.1.dist-info/METADATA
pycachera-4.5.1.dist-info/WHEEL
pycachera-4.5.1.dist-info/top_level.txt
pycachera-4.5.1.dist-info/RECORD
