Metadata-Version: 2.1
Name: pycachera
Version: 4.5.1
Summary: A powerfull python caching tool
Home-page: https://github.com/antolonappan/pycachera
Author: Anto Idicherian Lonappan
Author-email: mail@antolonappan.me
License-File: LICENSE
Requires-Dist: numpy
Requires-Dist: pandas
